merge_gbk_records/__init__.py
merge_gbk_records/__main__.py
merge_gbk_records-0.2.0.dist-info/LICENSE
merge_gbk_records-0.2.0.dist-info/METADATA
merge_gbk_records-0.2.0.dist-info/WHEEL
merge_gbk_records-0.2.0.dist-info/entry_points.txt
merge_gbk_records-0.2.0.dist-info/top_level.txt
merge_gbk_records-0.2.0.dist-info/RECORD
