Metadata-Version: 2.1
Name: merge-gbk-records
Version: 0.2.0
Summary: Merge multiple GenBank files using a spacer sequence
Home-page: https://github.com/kblin/merge-gbk-records/
Author: Kai Blin
Author-email: kblin@biosustain.dtu.dk
License: Apache Software License
Classifier: Programming Language :: Python
Classifier: Development Status :: 3 - Alpha
Classifier: Intended Audience :: Science/Research
Classifier: Topic :: Scientific/Engineering :: Bio-Informatics
Classifier: License :: OSI Approved :: Apache Software License
Classifier: Operating System :: OS Independent
License-File: LICENSE
Requires-Dist: biopython >=1.79
